pytest_toolbelt/__init__.py
pytest_toolbelt/fixtures.py
pytest_toolbelt/matchers.py
pytest_toolbelt/plugin.py
pytest_toolbelt/utils.py
pytest_toolbelt-0.1.0.dist-info/DESCRIPTION.rst
pytest_toolbelt-0.1.0.dist-info/METADATA
pytest_toolbelt-0.1.0.dist-info/RECORD
pytest_toolbelt-0.1.0.dist-info/WHEEL
pytest_toolbelt-0.1.0.dist-info/entry_points.txt
pytest_toolbelt-0.1.0.dist-info/metadata.json
pytest_toolbelt-0.1.0.dist-info/top_level.txt
