Metadata-Version: 2.0
Name: pytest-toolbelt
Version: 0.1.0
Summary: This is just a collection of utilities for pytest, but don't really belong in pytest proper.
Home-page: https://github.com/adalekin/pytest-toolbelt
Author: Aleksey Dalekin
Author-email: ald@investex.com.com
License: UNKNOWN
Keywords: rest client http pytest assert
Platform: UNKNOWN
Classifier: Development Status :: 3 - Alpha
Classifier: Intended Audience :: Developers
Classifier: Programming Language :: Python :: 3.5
Classifier: Programming Language :: Python :: 3.6
Classifier: Programming Language :: Python :: 3.7
Classifier: Topic :: Software Development :: Testing :: Unit
Requires-Dist: PyHamcrest (>=1.9.0)
Requires-Dist: requests (>=2.21.0)
